calq3-1.1.data/scripts/calQ3
src/__init__.py
calq3-1.1.dist-info/LICENSE
calq3-1.1.dist-info/METADATA
calq3-1.1.dist-info/WHEEL
calq3-1.1.dist-info/top_level.txt
calq3-1.1.dist-info/RECORD
