Metadata-Version: 2.1
Name: calq3
Version: 1.1
Summary: A script to calculate the Q3 score of secondary structure prediction
Home-page: https://github.com/nanjiang/calQ3-simple
Author: Nanjiang Shu
Author-email: nanjiang.shu@gmail.com
License: UNKNOWN
Platform: UNKNOWN
Classifier: Programming Language :: Python :: 3
Classifier: License :: OSI Approved :: MIT License
Classifier: Operating System :: OS Independent
